{
    "forge_marker": 1,
    "defaults": {
        "model": "minecraft:cube_column"
    },
    "variants": {
        "facing": {
            "north": {},
            "south": {"y": 180},
            "west":  {"y": 270},
            "east":  {"y": 90}
        },
		"type": {
			"top": {
				"textures": {
					"side": "scp:blocks/medwalltop",
					"end": "scp:blocks/officewallmiddle"
				}
			},
			"mid": {
				"textures": {
					"side": "scp:blocks/medwallmiddle",
					"end": "scp:blocks/medwallmiddle"
				}
			},
			"bottom": {
				"textures": {
					"side": "scp:blocks/medwallbottom",
					"end": "scp:blocks/medwallmiddle"	
				}
			},
			"center": {
				"textures": {
					"side": "scp:blocks/medwallmiddle",
					"end": "scp:blocks/medwallmiddle"
				}
			}
		}
    }
}